scheduler/__init__.py
scheduler/config.py
scheduler/json_types.py
scheduler/logging.py
scheduler/main.py
scheduler/scheduler.py
scheduler/server.py
scheduler/time_slot_generator.py
scheduler/models/__init__.py
scheduler/models/course.py
scheduler/models/day.py
scheduler/models/time_slot.py
scheduler/writers/__init__.py
scheduler/writers/csv_writer.py
scheduler/writers/json_writer.py
course_constraint_scheduler-2.6.1.dist-info/METADATA
course_constraint_scheduler-2.6.1.dist-info/WHEEL
course_constraint_scheduler-2.6.1.dist-info/entry_points.txt
course_constraint_scheduler-2.6.1.dist-info/licenses/LICENSE
course_constraint_scheduler-2.6.1.dist-info/RECORD
