Metadata-Version: 2.4
Name: course-constraint-scheduler
Version: 2.6.1
Summary: A constraint solver for generating schedules
License-Expression: MIT
License-File: LICENSE
Classifier: Development Status :: 4 - Beta
Classifier: Intended Audience :: Developers
Classifier: Programming Language :: Python :: 3
Classifier: Programming Language :: Python :: 3.12
Requires-Python: >=3.12
Requires-Dist: bidict~=0.23.1
Requires-Dist: click~=8.2.1
Requires-Dist: fastapi~=0.116.1
Requires-Dist: pydantic~=2.11.7
Requires-Dist: requests~=2.32.5
Requires-Dist: uvicorn[standard]~=0.35.0
Requires-Dist: z3-solver~=4.15.3.0
